vcl/__init__.py
vcl/client.py
vcl/exceptions.py
vcl/receipts.py
vcl_sdk-0.1.0.dist-info/METADATA
vcl_sdk-0.1.0.dist-info/WHEEL
vcl_sdk-0.1.0.dist-info/top_level.txt
vcl_sdk-0.1.0.dist-info/RECORD
