Metadata-Version: 2.4
Name: vcl-sdk
Version: 0.1.0
Summary: VCL Python SDK - Verified Compute Ledger for AI inference
Author: VCL Team
License: MIT
Project-URL: Homepage, https://github.com/ShokeyMalik/VCL
Project-URL: Documentation, https://github.com/ShokeyMalik/VCL#readme
Project-URL: Repository, https://github.com/ShokeyMalik/VCL
Keywords: vcl,ai,inference,receipts,verification,openai,anthropic
Classifier: Development Status :: 4 - Beta
Classifier: Intended Audience :: Developers
Classifier: License :: OSI Approved :: MIT License
Classifier: Programming Language :: Python :: 3
Classifier: Programming Language :: Python :: 3.8
Classifier: Programming Language :: Python :: 3.9
Classifier: Programming Language :: Python :: 3.10
Classifier: Programming Language :: Python :: 3.11
Classifier: Programming Language :: Python :: 3.12
Classifier: Topic :: Scientific/Engineering :: Artificial Intelligence
Requires-Python: >=3.8
Requires-Dist: requests>=2.28.0
Provides-Extra: dev
Requires-Dist: pytest>=7.0.0; extra == "dev"
Requires-Dist: pytest-asyncio>=0.20.0; extra == "dev"
Requires-Dist: black>=23.0.0; extra == "dev"
Requires-Dist: mypy>=1.0.0; extra == "dev"
Requires-Dist: types-requests>=2.28.0; extra == "dev"
